numpy_ext.py
numpy_ext-0.9.9.dist-info/LICENSE
numpy_ext-0.9.9.dist-info/METADATA
numpy_ext-0.9.9.dist-info/WHEEL
numpy_ext-0.9.9.dist-info/top_level.txt
numpy_ext-0.9.9.dist-info/RECORD
