Metadata-Version: 2.1
Name: numpy-ext
Version: 0.9.9
Summary: numpy extension
Home-page: https://github.com/3jane/numpy_ext
Author: 3jane.com
Author-email: contact@3jane.com
Classifier: Programming Language :: Python :: 3
Classifier: License :: OSI Approved :: MIT License
Classifier: Operating System :: OS Independent
Requires-Python: >=3.6
License-File: LICENSE
Requires-Dist: numpy <1.30.0,>=1.20.1
Requires-Dist: joblib <1.4.0,>=1.0.1
Provides-Extra: dev
Requires-Dist: flake8 ~=3.7.9 ; extra == 'dev'
Requires-Dist: pytest <8.0.0,>=4.3.0 ; extra == 'dev'
Requires-Dist: pytest-cov <5.0.0,>=2.8.1 ; extra == 'dev'
Requires-Dist: pandas <3.0.0,>=1.3.0 ; extra == 'dev'
Requires-Dist: numpydoc ~=0.9.2 ; extra == 'dev'
Requires-Dist: sphinx ~=2.4.4 ; extra == 'dev'
Requires-Dist: Jinja2 <3.1 ; extra == 'dev'
